spikeinterface/__init__.py
spikeinterface/full.py
spikeinterface/benchmark/__init__.py
spikeinterface/benchmark/benchmark_base.py
spikeinterface/benchmark/benchmark_clustering.py
spikeinterface/benchmark/benchmark_matching.py
spikeinterface/benchmark/benchmark_merging.py
spikeinterface/benchmark/benchmark_motion_estimation.py
spikeinterface/benchmark/benchmark_motion_interpolation.py
spikeinterface/benchmark/benchmark_peak_detection.py
spikeinterface/benchmark/benchmark_peak_localization.py
spikeinterface/benchmark/benchmark_peak_selection.py
spikeinterface/benchmark/benchmark_plot_tools.py
spikeinterface/benchmark/benchmark_sorter.py
spikeinterface/benchmark/benchmark_sorter_without_gt.py
spikeinterface/benchmark/benchmark_tools.py
spikeinterface/benchmark/residual_analysis.py
spikeinterface/comparison/__init__.py
spikeinterface/comparison/basecomparison.py
spikeinterface/comparison/collision.py
spikeinterface/comparison/comparisontools.py
spikeinterface/comparison/correlogram.py
spikeinterface/comparison/groundtruthstudy.py
spikeinterface/comparison/hybrid.py
spikeinterface/comparison/multicomparisons.py
spikeinterface/comparison/paircomparisons.py
spikeinterface/core/__init__.py
spikeinterface/core/analyzer_extension_core.py
spikeinterface/core/base.py
spikeinterface/core/baseevent.py
spikeinterface/core/baserecording.py
spikeinterface/core/baserecordingsnippets.py
spikeinterface/core/basesnippets.py
spikeinterface/core/basesorting.py
spikeinterface/core/binaryfolder.py
spikeinterface/core/binaryrecordingextractor.py
spikeinterface/core/channelsaggregationrecording.py
spikeinterface/core/channelslice.py
spikeinterface/core/core_tools.py
spikeinterface/core/datasets.py
spikeinterface/core/frameslicerecording.py
spikeinterface/core/frameslicesorting.py
spikeinterface/core/generate.py
spikeinterface/core/globals.py
spikeinterface/core/job_tools.py
spikeinterface/core/loading.py
spikeinterface/core/motion.py
spikeinterface/core/node_pipeline.py
spikeinterface-0.103.2.dist-info/licenses/LICENSE
spikeinterface-0.103.2.dist-info/METADATA
spikeinterface-0.103.2.dist-info/WHEEL
spikeinterface-0.103.2.dist-info/top_level.txt
spikeinterface-0.103.2.dist-info/RECORD
