Metadata-Version: 2.4
Name: spikeinterface
Version: 0.103.2
Summary: Python toolkit for analysis, visualization, and comparison of spike sorting output
Author-email: Alessio Buccino <alessiop.buccino@gmail.com>, Samuel Garcia <sam.garcia.die@gmail.com>
Project-URL: homepage, https://github.com/SpikeInterface/spikeinterface
Project-URL: repository, https://github.com/SpikeInterface/spikeinterface
Project-URL: documentation, https://spikeinterface.readthedocs.io/
Project-URL: changelog, https://spikeinterface.readthedocs.io/en/latest/whatisnew.html
Classifier: Programming Language :: Python :: 3 :: Only
Classifier: License :: OSI Approved :: MIT License
Classifier: Intended Audience :: Science/Research
Classifier: Operating System :: POSIX :: Linux
Classifier: Operating System :: Microsoft :: Windows
Classifier: Operating System :: MacOS
Classifier: Operating System :: OS Independent
Requires-Python: >=3.9
License-File: LICENSE
Requires-Dist: numpy>=1.20; python_version < "3.13"
Requires-Dist: numpy>=2.0.0; python_version >= "3.13"
Requires-Dist: threadpoolctl>=3.0.0
Requires-Dist: tqdm
Requires-Dist: zarr<3,>=2.18
Requires-Dist: neo>=0.14.3
Requires-Dist: probeinterface>=0.3.1
Requires-Dist: packaging
Requires-Dist: pydantic
Requires-Dist: numcodecs<0.16.0
Provides-Extra: extractors
Requires-Dist: MEArec>=1.8; extra == "extractors"
Requires-Dist: pynwb>=2.6.0; extra == "extractors"
Requires-Dist: hdmf-zarr>=0.11.0; extra == "extractors"
Requires-Dist: pyedflib>=0.1.30; extra == "extractors"
Requires-Dist: sonpy; python_version < "3.10" and extra == "extractors"
Requires-Dist: lxml; extra == "extractors"
Requires-Dist: scipy; extra == "extractors"
Requires-Dist: ibllib>=3.4.1; python_version >= "3.10" and extra == "extractors"
Requires-Dist: pymatreader>=0.0.32; extra == "extractors"
Requires-Dist: zugbruecke>=0.2; sys_platform != "win32" and extra == "extractors"
Provides-Extra: streaming-extractors
Requires-Dist: ibllib>=3.4.1; python_version >= "3.10" and extra == "streaming-extractors"
Requires-Dist: pynwb>=2.6.0; extra == "streaming-extractors"
Requires-Dist: fsspec; extra == "streaming-extractors"
Requires-Dist: aiohttp; extra == "streaming-extractors"
Requires-Dist: requests; extra == "streaming-extractors"
Requires-Dist: hdmf-zarr>=0.11.0; extra == "streaming-extractors"
Requires-Dist: remfile; extra == "streaming-extractors"
Requires-Dist: s3fs; extra == "streaming-extractors"
Provides-Extra: preprocessing
Requires-Dist: scipy; extra == "preprocessing"
Provides-Extra: full
Requires-Dist: h5py; extra == "full"
Requires-Dist: pandas; extra == "full"
Requires-Dist: scipy; extra == "full"
Requires-Dist: scikit-learn; extra == "full"
Requires-Dist: networkx; extra == "full"
Requires-Dist: distinctipy; extra == "full"
Requires-Dist: matplotlib>=3.6; extra == "full"
Requires-Dist: cuda-python>=11.8.6; platform_system != "Darwin" and extra == "full"
Requires-Dist: numba>=0.59; extra == "full"
Requires-Dist: skops; extra == "full"
Requires-Dist: huggingface_hub; extra == "full"
Provides-Extra: widgets
Requires-Dist: matplotlib; extra == "widgets"
Requires-Dist: ipympl; extra == "widgets"
Requires-Dist: ipywidgets; extra == "widgets"
Requires-Dist: sortingview>=0.12.0; extra == "widgets"
Provides-Extra: qualitymetrics
Requires-Dist: scikit-learn; extra == "qualitymetrics"
Requires-Dist: scipy; extra == "qualitymetrics"
Requires-Dist: pandas; extra == "qualitymetrics"
Requires-Dist: numba; extra == "qualitymetrics"
Provides-Extra: test-core
Requires-Dist: pytest<8.4.0; extra == "test-core"
Requires-Dist: pytest-dependency; extra == "test-core"
Requires-Dist: psutil; extra == "test-core"
Requires-Dist: pytest-mock; extra == "test-core"
Provides-Extra: test-extractors
Requires-Dist: pooch>=1.8.2; extra == "test-extractors"
Requires-Dist: datalad>=1.0.2; extra == "test-extractors"
Provides-Extra: test-preprocessing
Requires-Dist: ibllib>=3.4.1; python_version >= "3.10" and extra == "test-preprocessing"
Requires-Dist: torch; extra == "test-preprocessing"
Provides-Extra: test
Requires-Dist: pytest<8.4.0; extra == "test"
Requires-Dist: pytest-dependency; extra == "test"
Requires-Dist: pytest-cov; extra == "test"
Requires-Dist: psutil; extra == "test"
Requires-Dist: ibllib>=3.4.1; python_version >= "3.10" and extra == "test"
Requires-Dist: s3fs; extra == "test"
Requires-Dist: pynapple; extra == "test"
Requires-Dist: numba<0.61.0; python_version < "3.13" and extra == "test"
Requires-Dist: numba>=0.61.0; python_version >= "3.13" and extra == "test"
Requires-Dist: hdbscan>=0.8.33; extra == "test"
Requires-Dist: sortingview>=0.12.0; extra == "test"
Requires-Dist: torch; extra == "test"
Requires-Dist: skops; extra == "test"
Requires-Dist: huggingface_hub; extra == "test"
Requires-Dist: pytest-mock; extra == "test"
Provides-Extra: docs
Requires-Dist: Sphinx; extra == "docs"
Requires-Dist: ipython; extra == "docs"
Requires-Dist: sphinx_rtd_theme>=1.2; extra == "docs"
Requires-Dist: sphinx-gallery; extra == "docs"
Requires-Dist: sphinx-design; extra == "docs"
Requires-Dist: numpydoc; extra == "docs"
Requires-Dist: sphinxcontrib-jquery; extra == "docs"
Requires-Dist: autodoc_pydantic; extra == "docs"
Requires-Dist: MEArec; extra == "docs"
Requires-Dist: pandas; extra == "docs"
Requires-Dist: hdbscan>=0.8.33; extra == "docs"
Requires-Dist: numba; extra == "docs"
Requires-Dist: networkx; extra == "docs"
Requires-Dist: skops; extra == "docs"
Requires-Dist: scikit-learn; extra == "docs"
Requires-Dist: huggingface_hub; extra == "docs"
Provides-Extra: dev
Requires-Dist: spikeinterface[test]; extra == "dev"
Requires-Dist: spikeinterface[test_core]; extra == "dev"
Requires-Dist: spikeinterface[docs]; extra == "dev"
Requires-Dist: black; extra == "dev"
Requires-Dist: pre-commit; extra == "dev"
Dynamic: license-file
